makecmd/__init__.py
makecmd/makecmd.py
makecmd-1.8.dist-info/LICENSE
makecmd-1.8.dist-info/METADATA
makecmd-1.8.dist-info/WHEEL
makecmd-1.8.dist-info/entry_points.txt
makecmd-1.8.dist-info/top_level.txt
makecmd-1.8.dist-info/RECORD
