Metadata-Version: 2.1
Name: makecmd
Version: 1.8
Summary: UNKNOWN
Home-page: UNKNOWN
License: UNKNOWN
Platform: UNKNOWN
Requires-Dist: argparse
